CHANGES.md
LICENSE
MANIFEST.in
README.md
setup.py
chirptext/__init__.py
chirptext/__version__.py
chirptext/anhxa.py
chirptext/arsenal.py
chirptext/chio.py
chirptext/chirpnet.py
chirptext/cli.py
chirptext/daophay.py
chirptext/deko.py
chirptext/dekoigo.py
chirptext/dekomecab.py
chirptext/leutile.py
chirptext/luke.py
chirptext/sino.py
chirptext/texttaglib.py
chirptext.egg-info/PKG-INFO
chirptext.egg-info/SOURCES.txt
chirptext.egg-info/dependency_links.txt
chirptext.egg-info/top_level.txt
chirptext/data/luke/swadesh/1971.txt
chirptext/data/luke/swadesh/ranked.txt
chirptext/data/luke/swadesh/sign.txt
chirptext/data/sino/kangxi.csv
test/test_anhxa.py
test/test_arsenal.py
test/test_chirpnet.py
test/test_daophay.py
test/test_deko.py
test/test_io.py
test/test_leutile.py
test/test_luke.py
test/test_sino.py
test/test_ttlib.py