Metadata-Version: 2.1
Name: chirptext
Version: 0.1
Summary: A minimalist collection of text processing tools for Python 3
Home-page: https://github.com/letuananh/chirptext/
Author: Le Tuan Anh
Author-email: tuananh.ke@gmail.com
License: MIT License
Project-URL: Bug Tracker, https://github.com/letuananh/chirptext/issues
Project-URL: Source Code, https://github.com/letuananh/chirptext/
Keywords: nlp,mecab,language,linguistics,vietnamese,japanese,chinese,kanji,radical
Platform: any
Classifier: Programming Language :: Python
Classifier: Development Status :: 4 - Beta
Classifier: Natural Language :: English
Classifier: Environment :: Plugins
Classifier: Intended Audience :: Developers
Classifier: License :: OSI Approved :: MIT License
Classifier: Operating System :: OS Independent
Classifier: Topic :: Text Processing
Classifier: Topic :: Software Development :: Libraries :: Python Modules
Requires-Python: >=3.5
